setup.py
shapeshiftio/__init__.py
shapeshiftio/shapeshiftio.py
shapeshiftio.egg-info/PKG-INFO
shapeshiftio.egg-info/SOURCES.txt
shapeshiftio.egg-info/dependency_links.txt
shapeshiftio.egg-info/not-zip-safe
shapeshiftio.egg-info/top_level.txt