Metadata-Version: 1.0
Name: shapeshiftio
Version: 0.1.1
Summary: Python API for https://shapeshift.io
Home-page: http://github.com/abitfan/shapeshiftio
Author: A Bit Fan
Author-email: abitfan@ruggedinbox.com
License: MIT
Platform: UNKNOWN
